swandashboard/__init__.py
swandashboard/website.py
swandashboard-0.1.0.dist-info/LICENSE
swandashboard-0.1.0.dist-info/METADATA
swandashboard-0.1.0.dist-info/WHEEL
swandashboard-0.1.0.dist-info/top_level.txt
swandashboard-0.1.0.dist-info/RECORD
