Metadata-Version: 2.1
Name: swandashboard
Version: 0.1.0
Summary: A package to open SWAN Dashboard
Home-page: https://github.com/shivduttchoubey/swan.github.io
Author: Shivdutt Choubey
Author-email: shivduttchoubey@gmail.com
Classifier: Programming Language :: Python :: 3
Classifier: License :: OSI Approved :: MIT License
Classifier: Operating System :: OS Independent
Requires-Python: >=3.6
License-File: LICENSE
